{
  "longitudinal_controller": {
	"40": {
              "Kp": 0.8,
              "Kd": 0.2,
              "Ki": 0
        },
        "60": {
              "Kp": 0.7,
              "Kd": 0.2,
              "Ki": 0
        },
        "80": {
              "Kp": 0.5,
              "Kd": 0.15,
              "Ki": 0.05
        },
        "100": {
               "Kp": 0.5,
               "Kd": 0.1,
               "Ki": 0
        },
	"120": {
        	"Kp": 0.2,
                "Kd": 0.1,
                "Ki": 0.1
        }
  },	
  "latitudinal_controller": {
			
  "60": {
  	"Kp": 0.8,
        "Kd": 0.1,
        "Ki": 0.2
  },
  "80": {
  	"Kp": 0.6,
  	"Kd": 0.2,
  	"Ki": 0.1
  },
  "100": {
  	"Kp": 0.5,
        "Kd": 0.2,
        "Ki": 0.1
  },
  "120": {
  	"Kp": 0.4,
        "Kd": 0.2,
        "Ki": 0.2
  }
 }
}